pyfw/__init__.py
pyfw/exceptions.py
pyfw/api_1_1/__init__.py
pyfw/api_1_1/commonUserInfoViews.py
pyfw/auth/__init__.py
pyfw/auth/forms.py
pyfw/auth/views.py
pyfw/main/__init__.py
pyfw/main/errors.py
pyfw/main/forms.py
pyfw/main/models.py
pyfw/main/views.py
pyfw/system/__init__.py
pyfw/system/views.py
pyfw/util/JsonUtil.py
pyfw/util/__init__.py
pyfw/util/sshutil.py
pyfw-1.0.26.dist-info/LICENSE
pyfw-1.0.26.dist-info/METADATA
pyfw-1.0.26.dist-info/WHEEL
pyfw-1.0.26.dist-info/top_level.txt
pyfw-1.0.26.dist-info/RECORD
