Metadata-Version: 2.1
Name: pyfw
Version: 1.0.26
Summary: python framework
Home-page: https://github.com/wenanguo/pyfw
Author: Andrew Wen
Author-email: 79912844@qq.com
License: MIT Licence
Keywords: pip,cmcc,python,pyfw,framework
Platform: any
Requires-Dist: alembic (==1.0.0)
Requires-Dist: aniso8601 (==3.0.2)
Requires-Dist: asn1crypto (==0.24.0)
Requires-Dist: blinker (==1.4)
Requires-Dist: cffi (==1.11.5)
Requires-Dist: click (==6.7)
Requires-Dist: cryptography (==2.3)
Requires-Dist: dominate (==2.3.1)
Requires-Dist: Flask (==1.0.2)
Requires-Dist: Flask-Bootstrap (==3.3.7.1)
Requires-Dist: Flask-DebugToolbar (==0.10.1)
Requires-Dist: Flask-HTTPAuth (==3.2.4)
Requires-Dist: Flask-Login (==0.4.1)
Requires-Dist: Flask-Mail (==0.9.1)
Requires-Dist: Flask-Migrate (==2.2.1)
Requires-Dist: Flask-Moment (==0.6.0)
Requires-Dist: Flask-RESTful (==0.3.6)
Requires-Dist: Flask-Script (==2.0.6)
Requires-Dist: Flask-SQLAlchemy (==2.3.2)
Requires-Dist: Flask-WTF (==0.14.2)
Requires-Dist: idna (==2.7)
Requires-Dist: itsdangerous (==0.24)
Requires-Dist: Jinja2 (==2.10)
Requires-Dist: Mako (==1.0.7)
Requires-Dist: MarkupSafe (==1.0)
Requires-Dist: pycparser (==2.18)
Requires-Dist: PyMySQL (==0.9.2)
Requires-Dist: python-dateutil (==2.7.3)
Requires-Dist: python-editor (==1.0.3)
Requires-Dist: pytz (==2018.5)
Requires-Dist: six (==1.11.0)
Requires-Dist: SQLAlchemy (==1.2.10)
Requires-Dist: visitor (==0.1.3)
Requires-Dist: Werkzeug (==0.14.1)
Requires-Dist: WTForms (==2.2.1)
Requires-Dist: ForgeryPy (==0.1)
